unclogger/__init__.py
unclogger/defaults.py
unclogger/logger.py
unclogger/processors.py
unclogger-0.2.0.dist-info/METADATA
unclogger-0.2.0.dist-info/WHEEL
unclogger-0.2.0.dist-info/RECORD
